topsis/__init__.py
topsis/__main__.py
topsis_101803398-1.0.3.dist-info/LICENSE
topsis_101803398-1.0.3.dist-info/METADATA
topsis_101803398-1.0.3.dist-info/WHEEL
topsis_101803398-1.0.3.dist-info/top_level.txt
topsis_101803398-1.0.3.dist-info/RECORD
