Metadata-Version: 2.1
Name: topsis-101803398
Version: 1.0.3
Summary: Topsis implementation
Home-page: 
Author: Harshit Verma
Author-email: iamharshitverma114@gmail.com
License: MIT
Platform: UNKNOWN
Classifier: License :: OSI Approved :: MIT License
Classifier: Programming Language :: Python :: 3.6
Classifier: Programming Language :: Python :: 3.7
Classifier: Programming Language :: Python :: 3.8
Classifier: Programming Language :: Python :: 3.9
License-File: LICENSE
Requires-Dist: pandas
Requires-Dist: numpy
